{"cameraMode":{"drawMode":0,"name":"Shaded","section":"Shading Mode"},"sceneLighting":false,"audioPlay":false,"sceneViewState":{"m_AlwaysRefresh":false,"showFog":true,"showSkybox":false,"showFlares":true,"showImageEffects":true,"showParticleSystems":true,"showVisualEffectGraphs":true,"m_FxEnabled":true},"in2DMode":false,"pivot":{"x":-59.5,"y":3.917896270751953,"z":64.62515258789063},"rotation":{"x":-0.06922469288110733,"y":0.8674002885818481,"z":-0.4630047082901001,"w":-0.17490370571613313},"size":19.97657585144043,"orthographic":false}